abcsarang1/__init__.py
abcsarang1/main1.py
abcsarang1-0.0.1.dist-info/METADATA
abcsarang1-0.0.1.dist-info/WHEEL
abcsarang1-0.0.1.dist-info/top_level.txt
abcsarang1-0.0.1.dist-info/RECORD
